gatox/main.py
gatox/attack/attack.py
gatox/attack/cicd_attack.py
gatox/attack/payloads/payloads.py
gatox/attack/persistence/persistence_attack.py
gatox/attack/runner/c2_controller.py
gatox/attack/runner/payload_manager.py
gatox/attack/runner/repository_manager.py
gatox/attack/runner/webshell.py
gatox/attack/runner/webshell_utils.py
gatox/attack/secrets/secrets_attack.py
gatox/caching/cache_manager.py
gatox/caching/local_cache_manager.py
gatox/cli/cli.py
gatox/cli/colors.py
gatox/cli/output.py
gatox/cli/app/config.py
gatox/cli/attack/config.py
gatox/cli/enumeration/config.py
gatox/cli/persistence/config.py
gatox/cli/search/config.py
gatox/configuration/configuration_manager.py
gatox/configuration/notifications.json
gatox/configuration/workflow_parsing.json
gatox/enumerate/app_enumerate.py
gatox/enumerate/enumerate.py
gatox/enumerate/finegrained_enumeration.py
gatox/enumerate/organization.py
gatox/enumerate/recommender.py
gatox/enumerate/repository.py
gatox/enumerate/deep_dive/ingest_non_default.py
gatox/enumerate/ingest/ingest.py
gatox/enumerate/reports/actions.py
gatox/enumerate/reports/report.py
gatox/enumerate/reports/runners.py
gatox/enumerate/results/analysis_result.py
gatox/enumerate/results/artifact_poisoning_result.py
gatox/enumerate/results/complexity.py
gatox/enumerate/results/confidence.py
gatox/enumerate/results/dispatch_toctou_result.py
gatox/enumerate/results/injection_result.py
gatox/enumerate/results/issue_type.py
gatox/enumerate/results/pwn_request_result.py
gatox/enumerate/results/result_factory.py
gatox/enumerate/results/review_injection_result.py
gatox/git/git.py
gatox/git/utils.py
gatox/github/api.py
gatox/github/app_auth.py
gatox/github/gql_queries.py
gatox/github/search.py
gatox/mcp/mcp_server.py
gatox/models/composite.py
gatox/models/execution.py
gatox/models/organization.py
gatox/models/repository.py
gatox/models/runner.py
gatox/models/secret.py
gatox/models/workflow.py
gatox/notifications/send_webhook.py
gatox/search/search.py
gato_x-1.3.0.dist-info/METADATA
gato_x-1.3.0.dist-info/WHEEL
gato_x-1.3.0.dist-info/entry_points.txt
gato_x-1.3.0.dist-info/licenses/LICENSE
gato_x-1.3.0.dist-info/RECORD
