Metadata-Version: 2.4
Name: gato-x
Version: 1.3.0
Summary: GitHub Actions Enumeration and Attack Framework
Author-email: Adnan Khan <adnanthekhan@proton.me>
License-File: LICENSE
Classifier: Programming Language :: Python :: 3.10
Classifier: Programming Language :: Python :: 3.11
Classifier: Programming Language :: Python :: 3.12
Requires-Python: >=3.10
Requires-Dist: colorama
Requires-Dist: cryptography
Requires-Dist: httpx[http2,socks]
Requires-Dist: networkx
Requires-Dist: pyjwt[crypto]
Requires-Dist: pyyaml
Provides-Extra: docs
Requires-Dist: mkdocs; extra == 'docs'
Requires-Dist: mkdocs-material; extra == 'docs'
Provides-Extra: mcp
Requires-Dist: fastmcp; extra == 'mcp'
Provides-Extra: test
Requires-Dist: black; extra == 'test'
Requires-Dist: flake8; extra == 'test'
Requires-Dist: pytest; extra == 'test'
Requires-Dist: pytest-asyncio; extra == 'test'
Requires-Dist: pytest-cov; extra == 'test'
Requires-Dist: ruff; extra == 'test'
